Metadata-Version: 2.1
Name: cryptor
Version: 0.0.1
Summary: Simple tool for encrypting and decrypting files with RSA
Home-page: https://github.com/pavelsuk/cryptor
Author: Pavel Suk
Author-email: suk.pavel@gmail.com
License: UNKNOWN
Platform: UNKNOWN
Classifier: Programming Language :: Python :: 3
Classifier: License :: OSI Approved :: MIT License
Classifier: Operating System :: OS Independent
